mlxops/__init__.py
mlxops/saved_model.py
mlxops/components/__init__.py
mlxops/components/base.py
mlxops/components/data_components.py
mlxops/components/infered_feature_pipeline.py
mlxops/components/model_components.py
mlxops/components/serving_components.py
mlxops/pipeline/__init__.py
mlxops/pipeline/base.py
mlxops/pipeline/pipeline.py
mlxops/tests/__init__.py
mlxops/tests/test_pipeline.py
mlxops-0.1.0.dist-info/LICENSE
mlxops-0.1.0.dist-info/METADATA
mlxops-0.1.0.dist-info/WHEEL
mlxops-0.1.0.dist-info/top_level.txt
mlxops-0.1.0.dist-info/RECORD
