Metadata-Version: 2.1
Name: mlxops
Version: 0.1.0
Summary: Automating the ML Training Lifecycle with MLxOPS
Home-page: https://github.com/fernandonieuwveldt/mlxops_pipelines
Author: Fernando Nieuwveldt
Author-email: fdnieuwveldt@gmail.com
License: UNKNOWN
Platform: UNKNOWN
Classifier: Programming Language :: Python :: 3
Classifier: License :: OSI Approved :: MIT License
Classifier: Operating System :: OS Independent
Requires-Python: >=3.6.0
Requires-Dist: pandas (==1.0.0)
Requires-Dist: scikit-learn (==0.24.2)
